hashlib_tst.py
hashlib_tst-0.1.0.dist-info/METADATA
hashlib_tst-0.1.0.dist-info/WHEEL
hashlib_tst-0.1.0.dist-info/RECORD
